MANIFEST.in
README.rst
setup.py
flasker/__init__.py
flasker/__main__.py
flasker/project.py
flasker.egg-info/PKG-INFO
flasker.egg-info/SOURCES.txt
flasker.egg-info/dependency_links.txt
flasker.egg-info/entry_points.txt
flasker.egg-info/requires.txt
flasker.egg-info/top_level.txt
flasker/data/app/__init__.py
flasker/data/app/views.py
flasker/data/app/templates/base.html
flasker/data/app/templates/index.html
flasker/data/configs/default.cfg
flasker/ext/__init__.py
flasker/ext/api.py
flasker/ext/auth.py
flasker/ext/orm.py
flasker/ext/skl.py
flasker/ext/templates/auth/get_token_from_hash.html
flasker/ext/templates/auth/google_sign_in.html
flasker/test/__init__.py
flasker/test/test_project.py
flasker/test/test_util.py
flasker/util/__init__.py
flasker/util/flask.py
flasker/util/helpers.py
flasker/util/mixins.py
flasker/util/ndict.py
flasker/util/sqlalchemy.py