Metadata-Version: 1.0
Name: flasker
Version: 0.1.45
Summary: Flask, SQLAlchemy, and Celery integration
Home-page: http://mtth.github.com/flasker/
Author: Matthieu Monsch
Author-email: monsch@mit.edu
License: MIT
Platform: UNKNOWN
Classifier: Development Status :: 4 - Beta
Classifier: Intended Audience :: Developers
Classifier: License :: OSI Approved :: MIT License
Classifier: Topic :: System :: Distributed Computing
Classifier: Programming Language :: Python
